kflow/__init__.py
kflow/authn.py
kflow/extract.py
kflow/load.py
kflow/log.py
kflow/monitoring.py
kflow/tools.py
kflow-1.2.0.dist-info/licenses/LICENSE.txt
kflow-1.2.0.dist-info/METADATA
kflow-1.2.0.dist-info/WHEEL
kflow-1.2.0.dist-info/top_level.txt
kflow-1.2.0.dist-info/RECORD
