Metadata-Version: 2.4
Name: kflow
Version: 1.2.0
Summary: KLog.co package for ETLs with performance optimizations
Home-page: https://github.com/teu-ai/etl
Author: KLog.co Data & BI
Author-email: data@klog.co
License: Apache
Keywords: etl data science airflow redshift connection pooling
Classifier: Development Status :: 3 - Alpha
Classifier: License :: OSI Approved :: Apache Software License
Classifier: Programming Language :: Python :: 3.11
Classifier: Topic :: Software Development :: Libraries
License-File: LICENSE.txt
Requires-Dist: sqlalchemy
Requires-Dist: pandas
Requires-Dist: psycopg2-binary
Requires-Dist: boto3
Requires-Dist: smart_open
Requires-Dist: jinjasql
Requires-Dist: fastparquet
Requires-Dist: pyarrow
Dynamic: author
Dynamic: author-email
Dynamic: classifier
Dynamic: description
Dynamic: home-page
Dynamic: keywords
Dynamic: license
Dynamic: license-file
Dynamic: requires-dist
Dynamic: summary
